{"result_id": "186005", "URL": "https://lesmoutonsrebelles.com/au-fou-bill-gates-vaccinations-puces-electroniques-et-brevet-060606/", "timestamp": "2023-04-25 16:13:11 CEST+0200", "meta": {"description": "", "lang": "fr", "keywords": "", "favicon": "/wp-content/uploads/fbrfg/apple-touch-icon.png", "canonical": "https://lesmoutonsrebelles.com/au-fou-bill-gates-vaccinations-puces-electroniques-et-brevet-060606/", "encoding": "UTF-8"}, "image": null, "domain": "lesmoutonsrebelles.com", "title": "Au fou ! \u2026 Bill Gates, Vaccinations, puces \u00e9lectroniques et brevet 060606", "cleaned_text": "Il existe de nombreuses th\u00e9ories du complot \u2013 certains croient que des reptiliens dirigent le gouvernement am\u00e9ricain et d\u2019autres que Coca-Cola utilise le sang de b\u00e9b\u00e9s chr\u00e9tiens pour produire ses boissons gazeuses. Il y a des gens qui ont vu des \u00ab chemtrails \u00bb\n\n\n\n Souvent, les proph\u00e9ties des \u00c9critures sont interpr\u00e9t\u00e9es comme une d\u00e9couverte ou un \u00e9v\u00e9nement technologique. Mais il y a aussi des faits rationnels qu\u2019il n\u2019est pas logique de nier parce qu\u2019ils sont document\u00e9s. Il s\u2019agit notamment de l\u2019existence du club Bilderberg, du projet MK-Ultra de la CIA et du financement par George Soros d\u2019activit\u00e9s politiques douteuses dans un certain nombre de pays. Le cas d\u00e9crit ci-dessous se rapporte \u00e0 un fait officiellement document\u00e9, bien qu\u2019il ait quelque chose de plut\u00f4t biblique. Le brevet WO/2020/060606 [remarquez que 666 est le chiffre du diable ! NdT] a \u00e9t\u00e9 enregistr\u00e9 le 26 mars 2020. La demande de brevet a \u00e9t\u00e9 d\u00e9pos\u00e9e par Microsoft Technology Licensing, LLC, dirig\u00e9e par Bill Gates, le 20 juin 2019, et, le 22 avril 2020, le brevet a re\u00e7u un statut international. Le titre du brevet est \u00ab Syst\u00e8me de crypto-monnaie utilisant des donn\u00e9es sur l\u2019activit\u00e9 corporelle \u00bb.\n\nAlors, quelle est cette invention que les gens de Microsoft ont d\u00e9cid\u00e9 de breveter ?\n\nL\u2019abr\u00e9g\u00e9 de la demande de brevet en ligne le pr\u00e9cise :\n\nEn d\u2019autres termes, une puce sera ins\u00e9r\u00e9e dans le corps pour surveiller l\u2019activit\u00e9 physique quotidienne d\u2019une personne en \u00e9change de crypto-monnaie. Si les conditions sont remplies, la personne re\u00e7oit alors un bonus qui peut \u00eatre d\u00e9pens\u00e9 pour quelque chose.\n\nUne description d\u00e9taill\u00e9e de l\u2019\u00ab invention \u00bb fournit 28 concepts sur la mani\u00e8re dont l\u2019appareil pourrait \u00eatre utilis\u00e9.\n\nElle fournit \u00e9galement une liste des pays auxquels l\u2019invention est destin\u00e9e. Il s\u2019agit essentiellement de tous les membres des Nations unies et de quelques organisations r\u00e9gionales sp\u00e9cifi\u00e9es s\u00e9par\u00e9ment \u2013 l\u2019Office europ\u00e9en des brevets, l\u2019Organisation eurasienne des brevets et deux organisations africaines de protection de la propri\u00e9t\u00e9 intellectuelle.\n\nBien que l\u2019insertion de micro-puces dans le corps ne soit pas nouvelle, le programme ma\u00e7onnique d\u2019identification des jeunes enfants fonctionne aux \u00c9tats-Unis depuis un certain temps, et les personnes se disant cyborgs exposent divers implants, mais l\u2019implication de Microsoft est int\u00e9ressante. Et pourquoi le brevet a-t-il re\u00e7u le num\u00e9ro de code 060606 ? Est-ce une co\u00efncidence ou le choix d\u00e9lib\u00e9r\u00e9 de ce que le Livre des R\u00e9v\u00e9lations appelle le chiffre de la b\u00eate ?\n\nLe nom de Bill Gates est constamment mentionn\u00e9 ces jours-ci en rapport avec ses int\u00e9r\u00eats dans les soci\u00e9t\u00e9s pharmaceutiques, les vaccinations et le financement de l\u2019OMS. Bien que les m\u00e9dias mondialistes tentent de mettre en avant Bill Gates comme un grand philanthrope en le prot\u00e9geant des attaques et des critiques de toutes les fa\u00e7ons possibles, il est peu probable qu\u2019ils puissent dissimuler tout le r\u00e9seau de connexions.\n\nLa soci\u00e9t\u00e9 de Bill Gates est impliqu\u00e9e dans un autre projet, le projet d\u2019identification num\u00e9rique ID2020 Alliance. Sur la page d\u2019accueil du site, il est indiqu\u00e9 que le projet s\u2019int\u00e9resse \u00e0 la question des droits num\u00e9riques depuis 2016.\n\nEn 2018, l\u2019Alliance a travaill\u00e9 avec le Haut Commissariat des Nations unies pour les r\u00e9fugi\u00e9s. Outre Microsoft, l\u2019Alliance comprend la Fondation Rockefeller, le studio de design IDEO.org, avec des bureaux \u00e0 San Francisco et \u00e0 New York, la soci\u00e9t\u00e9 de conseil Accenture et Gavi, l\u2019Alliance pour la vaccination \u2013 une soci\u00e9t\u00e9 qui promeut et distribue activement divers vaccins dans le monde entier. Le secr\u00e9tariat de l\u2019Alliance est bas\u00e9 \u00e0 New York.\n\nIl est r\u00e9v\u00e9lateur que Gavi, l\u2019Alliance pour la vaccination, couvre principalement des pays d\u2019Afrique et d\u2019Asie. En Europe, l\u2019organisation n\u2019est active qu\u2019en Albanie, en Croatie, en Moldavie et en Ukraine et, dans le Caucase, en G\u00e9orgie, en Arm\u00e9nie et en Azerba\u00efdjan. Gavi, l\u2019Alliance pour la vaccination a \u00e9galement des liens avec la Fondation Bill & Melinda Gates, le Groupe de la Banque mondiale, l\u2019Organisation mondiale de la sant\u00e9 et l\u2019UNICEF. Tous ces organismes sont r\u00e9pertori\u00e9s comme partenaires fondateurs !\n\nDepuis f\u00e9vrier 2020 , Gavi, l\u2019Alliance pour la vaccination, se concentre sur la pand\u00e9mie de coronavirus. Le directeur g\u00e9n\u00e9ral de l\u2019organisation est le Dr Seth Berkley. Bien que le si\u00e8ge de Gavi, l\u2019Alliance pour la vaccination, soit \u00e0 Gen\u00e8ve, le Dr Berkley lui-m\u00eame, \u00e9pid\u00e9miologiste de formation, est originaire de New York. Depuis la fin des ann\u00e9es 80, il a travaill\u00e9 pendant huit ans \u00e0 la Fondation Rockefeller. Il est membre du Council on Foreign Relations. Il est \u00e9galement membre du conseil consultatif de l\u2019Acumen Fund, bas\u00e9 \u00e0 New York.\n\nUn autre lien a donc \u00e9t\u00e9 trouv\u00e9. Il est probablement pr\u00e9f\u00e9rable de laisser les interpr\u00e9tations th\u00e9ologiques du chiffre du brevet aux th\u00e9ologiens, mais il est clair qu\u2019il existe des liens \u00e9troits entre des organisations et des entreprises comme la Fondation Rockefeller, Microsoft, le lobby pharmaceutique et le groupe de la Banque mondiale, sans parler des prestataires de services secondaires. Ils essaient de jouer le r\u00f4le d\u2019un gouvernement supranational en se concentrant constamment sur le fait que, de nos jours, les gouvernements nationaux ne peuvent pas faire face seuls aux \u00e9pid\u00e9mies, maladies, famines, etc. Mais, comme la Chine l\u2019a montr\u00e9, ils le peuvent.\n\nMais l\u2019Occident ne peut et ne veut pas le reconna\u00eetre, en grande partie parce qu\u2019il ne veut pas partager le pouvoir. Les m\u00e9dias mondialistes vont donc poursuivre leurs campagnes d\u2019information, o\u00f9 la faute sera imput\u00e9e \u00e0 tout et tous sauf \u00e0 l\u2019Occident. Il est r\u00e9v\u00e9lateur qu\u2019en ce moment m\u00eame, alors que des informations suppl\u00e9mentaires sur le coronavirus commencent \u00e0 appara\u00eetre, les fausses histoires sur le r\u00f4le de la Chine dans l\u2019\u00e9pid\u00e9mie se multiplient et les statistiques sont manipul\u00e9es.\n\ntraduit par Herv\u00e9, relu par jj, pour le Saker Francophone", "opengraph": {"locale": "fr_FR", "type": "article", "title": "Au fou ! \u2026 Bill Gates, Vaccinations, puces \u00e9lectroniques et brevet 060606", "description": "Il existe de nombreuses th\u00e9ories\u00a0du complot \u2013 certains croient que des reptiliens dirigent le gouvernement am\u00e9ricain et d\u2019autres que Coca-Cola utilise le sang de b\u00e9b\u00e9s chr\u00e9tiens pour produire ses boissons gazeuses. Il y a des gens qui ont vu des\u00a0\u00ab\u00a0chemtrails\u00a0\u00bb Souvent, les proph\u00e9ties des \u00c9critures sont interpr\u00e9t\u00e9es comme une d\u00e9couverte ou un \u00e9v\u00e9nement technologique. Mais [\u2026]", "url": "https://lesmoutonsrebelles.com/au-fou-bill-gates-vaccinations-puces-electroniques-et-brevet-060606/", "site_name": "Les Moutons Rebelles", "article:publisher": "https://www.facebook.com/lesmoutonsrebelless/", "article:author": "https://www.facebook.com/lesmoutonsrebellesss/", "article:published_time": "2020-05-17T04:23:25+00:00", "image": "https://lesmoutonsrebelles.com/wp-content/uploads/2020/05/AP_739663431235_16x9_992.jpg", "image:width": "992", "image:height": "558"}, "tags": [], "tweets": [], "movies": [], "links": ["https://lesmoutonsrebelles.com/wp-content/uploads/2020/05/AP_739663431235_16x9_992.jpg", "https://patentscope.wipo.int/search/docs2/iasr/WO2020060606/html/q2VwnWZ1YPFEL6udLbHszDe4mIbB4-wKHkKhg5suIDTr70IAXy_oFDsYVDyPXvRFkDD2t5JvL7aoiTO2W8PEmzI093J8KzhNiiDQxI5zFb1WL9IAR5tj1KSHX31meU2B", "https://patentscope.wipo.int/search/en/detail.jsf?docId=WO2020060606&fbclid=IwAR19Drqz1E98QwkMrUm3bfTq2ll2denfK9naWwWKMq9qL3zrReDVErgsYbs", "https://patentscope.wipo.int/search/en/detail.jsf?docId=WO2020060606&tab=PCTCLAIMS", "http://www.mychip.org/home", "https://orientalreview.org/2020/02/23/human-dehumanisation/", "https://orientalreview.org/2020/04/22/coronavirus-is-changing-the-global-landscape-of-cybertechnology", "https://id2020.org/", "https://www.gavi.org/", "https://www.gavi.org/vaccineswork/covid19", "https://acumen.org/", "https://www.businessinsider.com/coronavirus-wuhan-china-abruptly-increases-death-toll-by-50-2020-4", "https://orientalreview.org/2020/04/29/bill-gates-vaccinations-microchips-and-patent-060606/", "https://lesakerfrancophone.fr/bill-gates-vaccinations-puces-electroniques-et-brevet-060606"], "authors": [""], "publish_date": "2020-05-17T04:23:25+00:00"}